meetSam/__init__.py
meetSam/__main__.py
meetSam/card_back.py
meetSam/card_front.py
meetSam/meet_sam.py
meetsam-0.0.4.dist-info/METADATA
meetsam-0.0.4.dist-info/WHEEL
meetsam-0.0.4.dist-info/top_level.txt
meetsam-0.0.4.dist-info/RECORD
