Metadata-Version: 2.4
Name: meetSam
Version: 0.0.4
Summary: A resume/website thing.
Project-URL: Homepage, https://meetsam.readthedocs.io
Project-URL: Documentation, https://meetsam.readthedocs.io
Project-URL: Repository, https://github.com/SamuelDonovan/meetSam
